baso_kontol/__init__.py
baso_kontol/__main__.py
baso_kontol/cli.py
baso_kontol-1.1.1.dist-info/METADATA
baso_kontol-1.1.1.dist-info/WHEEL
baso_kontol-1.1.1.dist-info/entry_points.txt
baso_kontol-1.1.1.dist-info/top_level.txt
baso_kontol-1.1.1.dist-info/RECORD
